pbsm/Lexer.g4
pbsm/Lexer.interp
pbsm/Lexer.py
pbsm/Lexer.tokens
pbsm/Makefile
pbsm/__init__.py
pbsm/__main__.py
pbsm/core.py
pbsm/version.py
pbsm-0.3.1.dist-info/METADATA
pbsm-0.3.1.dist-info/WHEEL
pbsm-0.3.1.dist-info/licenses/LICENSE
pbsm-0.3.1.dist-info/RECORD
