Metadata-Version: 2.1
Name: pbsm
Version: 0.3.1
Summary: Python based stack machine
Author-email: Andras Lehn <andreas.lehn@icloud.com>
License: MIT License
License-File: LICENSE
Classifier: Development Status :: 2 - Pre-Alpha
Classifier: Programming Language :: Python
Requires-Dist: antlr4-python3-runtime
